keras_swin_unet/__init__.py
keras_swin_unet/swin_layers.py
keras_swin_unet/transformer_layers.py
keras_swin_unet/util_layers.py
keras_swin_unet/utils.py
swin_transformer/AUC_LOSS.py
swin_transformer/__init__.py
swin_transformer/api.py
swin_transformer/cli.py
swin_transformer/data_loader.py
swin_transformer/main.py
swin_transformer/metrics.py
swin_transformer/model_loader.py
swin_transformer/split_data.py
keras_swin_unet-0.1.8.dist-info/LICENSE
keras_swin_unet-0.1.8.dist-info/METADATA
keras_swin_unet-0.1.8.dist-info/WHEEL
keras_swin_unet-0.1.8.dist-info/entry_points.txt
keras_swin_unet-0.1.8.dist-info/RECORD
