Metadata-Version: 2.3
Name: keras-swin-unet
Version: 0.1.8
Summary: A robust, flexible Swin‑UNet package built with Keras/TensorFlow for image‑segmentation tasks.
License: MIT
Author: L‑A‑Sandhu
Author-email: laeeq.aslam.100@gmail.com
Requires-Python: >=3.10,<3.11
Classifier: License :: OSI Approved :: MIT License
Classifier: Programming Language :: Python :: 3
Classifier: Programming Language :: Python :: 3.10
Requires-Dist: matplotlib (>=3.10.1,<4.0.0)
Requires-Dist: numpy (>=1.26.4,<2.0.0)
Requires-Dist: pillow (>=11.2.1,<12.0.0)
Requires-Dist: scikit-learn (>=1.6.1,<2.0.0)
Requires-Dist: scipy (>=1.15.2,<2.0.0)
Requires-Dist: tensorflow (>=2.19.0,<3.0.0)
Requires-Dist: tqdm (>=4.67.1,<5.0.0)
